daq/__init__.py
daq/io.py
pandas_sigproc/__init__.py
pandas_sigproc/extension.py
pandas_sigproc/tools.py
pandas_sigproc-1.0.5.dist-info/LICENSE
pandas_sigproc-1.0.5.dist-info/METADATA
pandas_sigproc-1.0.5.dist-info/WHEEL
pandas_sigproc-1.0.5.dist-info/top_level.txt
pandas_sigproc-1.0.5.dist-info/RECORD
