Metadata-Version: 2.1
Name: pandas-sigproc
Version: 1.0.5
Summary: Useful pandas extensions for detailed signal processing
Home-page: https://github.com/johns7591/pandas-sigproc
Author: John Scanlon
License: UNKNOWN
Platform: UNKNOWN
License-File: LICENSE
Requires-Dist: numpy~=1.22.1
Requires-Dist: scipy~=1.7.3
Requires-Dist: matplotlib~=3.5.1
Requires-Dist: pandas~=1.4.0
Requires-Dist: sounddevice==0.4.4
Requires-Dist: endaq~=1.5.1
Requires-Dist: rainflow~=3.1.1
